beavis/__init__.py
beavis/bcolors.py
beavis/equality.py
beavis/prettytable.py
beavis/six.py
beavis/testing.py
beavis-0.3.0.dist-info/LICENSE.md
beavis-0.3.0.dist-info/WHEEL
beavis-0.3.0.dist-info/METADATA
beavis-0.3.0.dist-info/RECORD
