Metadata-Version: 2.1
Name: beavis
Version: 0.3.0
Summary: 
Author: MrPowers
Author-email: matthewkevinpowers@gmail.com
Requires-Python: >=3.9,<4.0
Classifier: Programming Language :: Python :: 3
Classifier: Programming Language :: Python :: 3.9
Classifier: Programming Language :: Python :: 3.10
Classifier: Programming Language :: Python :: 3.11
Requires-Dist: pandas (>=1.0.0)
